vrp/__init__.py
vrp/run.py
vrp/base/__init__.py
vrp/base/logger.py
vrp/base/utils.py
vrp/excel/__init__.py
vrp/excel/define.py
vrp/excel/process.py
vrp/excel/sink.py
vrp/excel/utils.py
tools_vrp-0.2.0.dist-info/entry_points.txt
tools_vrp-0.2.0.dist-info/LICENSE
tools_vrp-0.2.0.dist-info/WHEEL
tools_vrp-0.2.0.dist-info/METADATA
tools_vrp-0.2.0.dist-info/RECORD
