Metadata-Version: 2.1
Name: tools_vrp
Version: 0.2.0
Summary: valuation report parser
Author-email: fengbing <bing.feng@iquantex.com>
Classifier: License :: OSI Approved :: MIT License
Project-URL: Home, https://www.iquantex.com
